uw_mailman/VERSION
uw_mailman/__init__.py
uw_mailman/basic_list.py
uw_mailman/course_list.py
uw_mailman/dao.py
uw_mailman/instructor_term_list.py
uw_mailman/term_list.py
uw_mailman/test.py
uw_mailman/util.py
uw_mailman/resources/mailman/file/__mock_key__/admin/v1.0/uwnetid/available/_uwnetid_bbio180a_au12
uw_mailman/resources/mailman/file/__mock_key__/admin/v1.0/uwnetid/available/_uwnetid_bbio180a_au13
uw_mailman/resources/mailman/file/__mock_key__/admin/v1.0/uwnetid/available/_uwnetid_bill_au13
uw_mailman/resources/mailman/file/__mock_key__/admin/v1.0/uwnetid/available/_uwnetid_math125g_su13
uw_mailman/resources/mailman/file/__mock_key__/admin/v1.0/uwnetid/available/_uwnetid_multi_bbio180a_au13
uw_mailman/resources/mailman/file/__mock_key__/admin/v1.0/uwnetid/available/_uwnetid_multi_math125a_su13
uw_mailman/resources/mailman/file/__mock_key__/admin/v1.0/uwnetid/available/_uwnetid_multi_math125g_su13
uw_mailman/resources/mailman/file/__mock_key__/admin/v1.0/uwnetid/available/_uwnetid_tbus310a_au13
uw_mailman/resources/mailman/file/__mock_key__/admin/v1.0/uwnetid/available/_uwnetid_tbus310a_sp13
uw_mailman/resources/mailman/file/uw_list_manager/api/v1/list/bbio180a_au12/exists
uw_mailman/resources/mailman/file/uw_list_manager/api/v1/list/bbio180a_au13/exists
uw_mailman/resources/mailman/file/uw_list_manager/api/v1/list/bbio180a_su13/exists
uw_mailman/resources/mailman/file/uw_list_manager/api/v1/list/bill_au13/exists
uw_mailman/resources/mailman/file/uw_list_manager/api/v1/list/math125g_su13/exists
uw_mailman/resources/mailman/file/uw_list_manager/api/v1/list/multi_bbio180a_au13/exists
uw_mailman/resources/mailman/file/uw_list_manager/api/v1/list/multi_math125a_su13/exists
uw_mailman/resources/mailman/file/uw_list_manager/api/v1/list/multi_math125g_su13/exists
uw_mailman/resources/mailman/file/uw_list_manager/api/v1/list/tbus310a_au13/exists
uw_mailman/resources/mailman/file/uw_list_manager/api/v1/list/tbus310a_sp13/exists
uw_mailman/tests/__init__.py
uw_restclients_mailman-2.1.dist-info/licenses/LICENSE
uw_restclients_mailman-2.1.dist-info/METADATA
uw_restclients_mailman-2.1.dist-info/WHEEL
uw_restclients_mailman-2.1.dist-info/top_level.txt
uw_restclients_mailman-2.1.dist-info/RECORD
