Metadata-Version: 2.4
Name: UW-RestClients-Mailman
Version: 2.1
Summary: A library for connecting to the mailman API
Home-page: https://github.com/uw-it-aca/uw-restclients-mailman
Author: UW-IT SETS
Author-email: aca-it@uw.edu
License: Apache License, Version 2.0
Classifier: Intended Audience :: Developers
Classifier: License :: OSI Approved :: Apache Software License
Classifier: Operating System :: OS Independent
Classifier: Programming Language :: Python
License-File: LICENSE
Requires-Dist: UW-restClients-core
Requires-Dist: UW-restClients-sws
Dynamic: author
Dynamic: author-email
Dynamic: classifier
Dynamic: description
Dynamic: home-page
Dynamic: license
Dynamic: license-file
Dynamic: requires-dist
Dynamic: summary
